funutil/__init__.py
funutil/cache/__init__.py
funutil/cache/box.py
funutil/cache/core.py
funutil/cache/disk.py
funutil/cache/tools.py
funutil/convert/__init__.py
funutil/convert/curl2py.py
funutil/html/pyhtml.py
funutil/math/__init__.py
funutil/math/prime.py
funutil/paper/Paper.py
funutil/paper/Paper2.py
funutil/path/__init__.py
funutil/path/core.py
funutil/time/__init__.py
funutil/time/timer.py
funutil/util/__init__.py
funutil/util/log.py
funutil/util/map.py
funutil/util/package.py
funutil/util/path.py
funutil/util/retrying.py
funutil/util/time.py
funutil-1.0.60.dist-info/METADATA
funutil-1.0.60.dist-info/WHEEL
funutil-1.0.60.dist-info/top_level.txt
funutil-1.0.60.dist-info/RECORD
