Metadata-Version: 2.1
Name: funutil
Version: 1.0.60
Summary: funutil
Author-email: 牛哥 <niuliangtao@qq.com>, farfarfun <farfarfun@qq.com>
Maintainer-email: 牛哥 <niuliangtao@qq.com>, farfarfun <farfarfun@qq.com>
Project-URL: Organization, https://github.com/farfarfun
Project-URL: Repository, https://github.com/farfarfun/funutil
Project-URL: Releases, https://github.com/farfarfun/funutil/releases
Requires-Python: >=3.8
Requires-Dist: cachebox ==5.0.1
Requires-Dist: cachetools >=4.2.4
Requires-Dist: diskcache >=5.6.3
Requires-Dist: loguru >=0.7.2
